instantgit/__init__.py
instantgit/cli.py
instantgit/templates.py
instantgit-0.1.0.dist-info/METADATA
instantgit-0.1.0.dist-info/WHEEL
instantgit-0.1.0.dist-info/entry_points.txt
instantgit-0.1.0.dist-info/licenses/LICENSE
instantgit-0.1.0.dist-info/RECORD
