Metadata-Version: 2.4
Name: instantgit
Version: 0.1.0
Summary: A comprehensive .gitignore template manager
Author: InstantGit Team
License-File: LICENSE
Classifier: License :: OSI Approved :: MIT License
Classifier: Operating System :: OS Independent
Classifier: Programming Language :: Python :: 3
Requires-Python: >=3.7
